sample_app/__init__.py
sample_app/mod1.py
sample_app-1.0.3.data/scripts/text-spider
sample_app-1.0.3.dist-info/DESCRIPTION.rst
sample_app-1.0.3.dist-info/METADATA
sample_app-1.0.3.dist-info/RECORD
sample_app-1.0.3.dist-info/WHEEL
sample_app-1.0.3.dist-info/metadata.json
sample_app-1.0.3.dist-info/top_level.txt
